{
    "id": 0,
    "identifier": "317ea3fc-e72c-4c6f-a89f-c621142a785a",
    "version": "1",
    "isEnabled": true,
    "isDebugMode": false,
    "name": "Playbook Action 2",
    "creator": "bc91ae5a-65ad-40bd-aa54-2cfabde49698",
    "modifiedBy": "973d7959-bcd7-48fa-8b56-37fa8244951d",
    "priority": 2,
    "description": "",
    "environments": [
        "*"
    ],
    "categoryName": "Default",
    "categoryId": 1,
    "originalPlaybookIdentifier": "317ea3fc-e72c-4c6f-a89f-c621142a785a",
    "creationTimeUnixTimeInMs": 1751277286145,
    "modificationTimeUnixTimeInMs": 1751277286145,
    "trigger": {
        "id": 0,
        "identifier": "2275b068-509e-44ee-a603-2d3cb6eec787",
        "type": 8,
        "logicalOperator": 0,
        "conditions": [
            {
                "fieldName": "",
                "value": "",
                "matchType": 0
            }
        ]
    },
    "steps": [
        {
            "parallelActions": [],
            "identifier": "14936ab1-45ce-4897-853c-948e168a4c9f",
            "originalStepIdentifier": "14936ab1-45ce-4897-853c-948e168a4c9f",
            "isAutomatic": true,
            "isSkippable": false,
            "instanceName": "VirusTotalV3_Enrich IOC_1",
            "name": "VirusTotalV3_Enrich IOC",
            "integration": "VirusTotalV3",
            "description": "Enrich IOCs using information from VirusTotal.",
            "actionProvider": "Scripts",
            "actionName": "VirusTotalV3_Enrich IOC",
            "type": 0,
            "parameters": [
                {
                    "name": "AssignedUsers",
                    "value": null,
                    "type": null,
                    "isMandatory": false,
                    "defaultValue": null,
                    "id": 0,
                    "creationTimeUnixTimeInMs": 0,
                    "modificationTimeUnixTimeInMs": 0,
                    "additionalProperties": {}
                },
                {
                    "name": "DynamicInjectionInstancePlaceholder",
                    "value": "",
                    "type": null,
                    "isMandatory": false,
                    "defaultValue": null,
                    "id": 0,
                    "creationTimeUnixTimeInMs": 0,
                    "modificationTimeUnixTimeInMs": 0,
                    "additionalProperties": {}
                },
                {
                    "name": "FallbackIntegrationInstance",
                    "value": "74f874b3-c98a-413b-99bb-845f8fecc5c8",
                    "type": null,
                    "isMandatory": false,
                    "defaultValue": null,
                    "id": 0,
                    "creationTimeUnixTimeInMs": 0,
                    "modificationTimeUnixTimeInMs": 0,
                    "additionalProperties": {},
                    "FallbackInstanceDisplayName": "VirusTotalV3_4"
                },
                {
                    "name": "FetchInstanceByName",
                    "value": "false",
                    "type": null,
                    "isMandatory": false,
                    "defaultValue": null,
                    "id": 0,
                    "creationTimeUnixTimeInMs": 0,
                    "modificationTimeUnixTimeInMs": 0,
                    "additionalProperties": {}
                },
                {
                    "name": "HasApprovalLink",
                    "value": null,
                    "type": null,
                    "isMandatory": false,
                    "defaultValue": null,
                    "id": 0,
                    "creationTimeUnixTimeInMs": 0,
                    "modificationTimeUnixTimeInMs": 0,
                    "additionalProperties": {}
                },
                {
                    "name": "IntegrationInstance",
                    "value": "AutomaticEnvironment",
                    "type": null,
                    "isMandatory": false,
                    "defaultValue": null,
                    "id": 0,
                    "creationTimeUnixTimeInMs": 0,
                    "modificationTimeUnixTimeInMs": 0,
                    "additionalProperties": {}
                },
                {
                    "name": "MessageToAssignee",
                    "value": null,
                    "type": null,
                    "isMandatory": false,
                    "defaultValue": null,
                    "id": 0,
                    "creationTimeUnixTimeInMs": 0,
                    "modificationTimeUnixTimeInMs": 0,
                    "additionalProperties": {}
                },
                {
                    "name": "PendingActionTimeout",
                    "value": null,
                    "type": null,
                    "isMandatory": false,
                    "defaultValue": null,
                    "id": 0,
                    "creationTimeUnixTimeInMs": 0,
                    "modificationTimeUnixTimeInMs": 0,
                    "additionalProperties": {}
                },
                {
                    "name": "ScriptName",
                    "value": "VirusTotalV3_Enrich IOC",
                    "type": null,
                    "isMandatory": false,
                    "defaultValue": null,
                    "id": 0,
                    "creationTimeUnixTimeInMs": 0,
                    "modificationTimeUnixTimeInMs": 0,
                    "additionalProperties": {}
                },
                {
                    "name": "ScriptParametersEntityFields",
                    "value": "{\"IOC Type\":\"Filehash\",\"IOCs\":\"1313244\",\"Widget Theme\":\"Dark\",\"Fetch Widget\":true}",
                    "type": null,
                    "isMandatory": false,
                    "defaultValue": null,
                    "id": 0,
                    "creationTimeUnixTimeInMs": 0,
                    "modificationTimeUnixTimeInMs": 0,
                    "additionalProperties": {}
                },
                {
                    "name": "SelectedScopeName",
                    "value": "All entities",
                    "type": null,
                    "isMandatory": false,
                    "defaultValue": null,
                    "id": 0,
                    "creationTimeUnixTimeInMs": 0,
                    "modificationTimeUnixTimeInMs": 0,
                    "additionalProperties": {}
                },
                {
                    "name": "UseEntitiesLoopScope",
                    "value": null,
                    "type": null,
                    "isMandatory": false,
                    "defaultValue": null,
                    "id": 0,
                    "creationTimeUnixTimeInMs": 0,
                    "modificationTimeUnixTimeInMs": 0,
                    "additionalProperties": {}
                }
            ],
            "autoSkipOnFailure": false,
            "isDebugMockData": false,
            "debugData": null,
            "parentStepContainerId": null,
            "workflowIdentifier": "317ea3fc-e72c-4c6f-a89f-c621142a785a",
            "isTouchedByAi": false,
            "startLoopStepIdentifier": null,
            "id": 0,
            "creationTimeUnixTimeInMs": 1751277286145,
            "modificationTimeUnixTimeInMs": 1751277286145,
            "additionalProperties": {}
        },
        {
            "parallelActions": [],
            "identifier": "1c9341ea-f3e6-4f83-a517-289427e1fb0c",
            "originalStepIdentifier": "1c9341ea-f3e6-4f83-a517-289427e1fb0c",
            "isAutomatic": true,
            "isSkippable": false,
            "instanceName": "VirusTotalV3_Download File_1",
            "name": "VirusTotalV3_Download File",
            "integration": "VirusTotalV3",
            "description": "Download file from VirusTotal. Supported entities: Filehash. Note: this action requires a VT Enterprise token. Only MD5, SHA-1, SHA-256 hashes are supported.",
            "actionProvider": "Scripts",
            "actionName": "VirusTotalV3_Download File",
            "type": 0,
            "parameters": [
                {
                    "name": "AssignedUsers",
                    "value": null,
                    "type": null,
                    "isMandatory": false,
                    "defaultValue": null,
                    "id": 0,
                    "creationTimeUnixTimeInMs": 0,
                    "modificationTimeUnixTimeInMs": 0,
                    "additionalProperties": {}
                },
                {
                    "name": "DynamicInjectionInstancePlaceholder",
                    "value": "",
                    "type": null,
                    "isMandatory": false,
                    "defaultValue": null,
                    "id": 0,
                    "creationTimeUnixTimeInMs": 0,
                    "modificationTimeUnixTimeInMs": 0,
                    "additionalProperties": {}
                },
                {
                    "name": "FallbackIntegrationInstance",
                    "value": "ac89693a-cba6-477b-a1ac-df00a7f82a58",
                    "type": null,
                    "isMandatory": false,
                    "defaultValue": null,
                    "id": 0,
                    "creationTimeUnixTimeInMs": 0,
                    "modificationTimeUnixTimeInMs": 0,
                    "additionalProperties": {},
                    "FallbackInstanceDisplayName": "VirusTotalV3_5"
                },
                {
                    "name": "FetchInstanceByName",
                    "value": "false",
                    "type": null,
                    "isMandatory": false,
                    "defaultValue": null,
                    "id": 0,
                    "creationTimeUnixTimeInMs": 0,
                    "modificationTimeUnixTimeInMs": 0,
                    "additionalProperties": {}
                },
                {
                    "name": "HasApprovalLink",
                    "value": null,
                    "type": null,
                    "isMandatory": false,
                    "defaultValue": null,
                    "id": 0,
                    "creationTimeUnixTimeInMs": 0,
                    "modificationTimeUnixTimeInMs": 0,
                    "additionalProperties": {}
                },
                {
                    "name": "IntegrationInstance",
                    "value": "AutomaticEnvironment",
                    "type": null,
                    "isMandatory": false,
                    "defaultValue": null,
                    "id": 0,
                    "creationTimeUnixTimeInMs": 0,
                    "modificationTimeUnixTimeInMs": 0,
                    "additionalProperties": {}
                },
                {
                    "name": "MessageToAssignee",
                    "value": null,
                    "type": null,
                    "isMandatory": false,
                    "defaultValue": null,
                    "id": 0,
                    "creationTimeUnixTimeInMs": 0,
                    "modificationTimeUnixTimeInMs": 0,
                    "additionalProperties": {}
                },
                {
                    "name": "PendingActionTimeout",
                    "value": null,
                    "type": null,
                    "isMandatory": false,
                    "defaultValue": null,
                    "id": 0,
                    "creationTimeUnixTimeInMs": 0,
                    "modificationTimeUnixTimeInMs": 0,
                    "additionalProperties": {}
                },
                {
                    "name": "ScriptName",
                    "value": "VirusTotalV3_Download File",
                    "type": null,
                    "isMandatory": false,
                    "defaultValue": null,
                    "id": 0,
                    "creationTimeUnixTimeInMs": 0,
                    "modificationTimeUnixTimeInMs": 0,
                    "additionalProperties": {}
                },
                {
                    "name": "ScriptParametersEntityFields",
                    "value": "{\"Download Folder Path\":\"/tmp/tmp\",\"Overwrite\":true}",
                    "type": null,
                    "isMandatory": false,
                    "defaultValue": null,
                    "id": 0,
                    "creationTimeUnixTimeInMs": 0,
                    "modificationTimeUnixTimeInMs": 0,
                    "additionalProperties": {}
                },
                {
                    "name": "SelectedScopeName",
                    "value": "All entities",
                    "type": null,
                    "isMandatory": false,
                    "defaultValue": null,
                    "id": 0,
                    "creationTimeUnixTimeInMs": 0,
                    "modificationTimeUnixTimeInMs": 0,
                    "additionalProperties": {}
                },
                {
                    "name": "UseEntitiesLoopScope",
                    "value": null,
                    "type": null,
                    "isMandatory": false,
                    "defaultValue": null,
                    "id": 0,
                    "creationTimeUnixTimeInMs": 0,
                    "modificationTimeUnixTimeInMs": 0,
                    "additionalProperties": {}
                }
            ],
            "autoSkipOnFailure": false,
            "isDebugMockData": false,
            "debugData": null,
            "parentStepContainerId": null,
            "workflowIdentifier": "317ea3fc-e72c-4c6f-a89f-c621142a785a",
            "isTouchedByAi": false,
            "startLoopStepIdentifier": null,
            "id": 0,
            "creationTimeUnixTimeInMs": 1751277286145,
            "modificationTimeUnixTimeInMs": 1751277286145,
            "additionalProperties": {}
        },
        {
            "parallelActions": [],
            "identifier": "25598f92-e1bb-44f3-9aa7-3d0fa9f3608d",
            "originalStepIdentifier": "25598f92-e1bb-44f3-9aa7-3d0fa9f3608d",
            "isAutomatic": true,
            "isSkippable": false,
            "instanceName": "New Block 2_1",
            "name": "New Block 2",
            "integration": "Siemplify",
            "description": "An embedded workflow that can receive inputs and return an output.",
            "actionProvider": "Flow",
            "actionName": "NestedAction",
            "type": 5,
            "parameters": [
                {
                    "name": "AssignedUsers",
                    "value": null,
                    "type": null,
                    "isMandatory": false,
                    "defaultValue": null,
                    "id": 0,
                    "creationTimeUnixTimeInMs": 0,
                    "modificationTimeUnixTimeInMs": 0,
                    "additionalProperties": {}
                },
                {
                    "name": "HasApprovalLink",
                    "value": null,
                    "type": null,
                    "isMandatory": false,
                    "defaultValue": null,
                    "id": 0,
                    "creationTimeUnixTimeInMs": 0,
                    "modificationTimeUnixTimeInMs": 0,
                    "additionalProperties": {}
                },
                {
                    "name": "MessageToAssignee",
                    "value": null,
                    "type": null,
                    "isMandatory": false,
                    "defaultValue": null,
                    "id": 0,
                    "creationTimeUnixTimeInMs": 0,
                    "modificationTimeUnixTimeInMs": 0,
                    "additionalProperties": {}
                },
                {
                    "name": "NestedWorkflowIdentifier",
                    "value": "10bcab2e-b9df-4f87-b0af-4dcf80b85369",
                    "type": null,
                    "isMandatory": false,
                    "defaultValue": null,
                    "id": 0,
                    "creationTimeUnixTimeInMs": 0,
                    "modificationTimeUnixTimeInMs": 0,
                    "additionalProperties": {}
                },
                {
                    "name": "NestedWorkflowInputs",
                    "value": "[]",
                    "type": null,
                    "isMandatory": false,
                    "defaultValue": null,
                    "id": 0,
                    "creationTimeUnixTimeInMs": 0,
                    "modificationTimeUnixTimeInMs": 0,
                    "additionalProperties": {}
                },
                {
                    "name": "PendingActionTimeout",
                    "value": null,
                    "type": null,
                    "isMandatory": false,
                    "defaultValue": null,
                    "id": 0,
                    "creationTimeUnixTimeInMs": 0,
                    "modificationTimeUnixTimeInMs": 0,
                    "additionalProperties": {}
                },
                {
                    "name": "NestedWorkflowSteps",
                    "value": "[{\"identifier\":\"0bc0aafe-0ad8-4c99-8208-0f3b3af75194\",\"integration\":\"VirusTotalV3\",\"actionName\":\"VirusTotalV3_Add Vote To Entity\",\"instanceName\":\"VirusTotalV3_Add Vote To Entity_1\",\"stepType\":0},{\"identifier\":\"de0c25a8-79e7-4530-bc67-a410ea9a171d\",\"integration\":\"VirusTotalV3\",\"actionName\":\"VirusTotalV3_Enrich IP\",\"instanceName\":\"VirusTotalV3_Enrich IP_1\",\"stepType\":0}]",
                    "type": null,
                    "isMandatory": false,
                    "defaultValue": null,
                    "id": 0,
                    "creationTimeUnixTimeInMs": 0,
                    "modificationTimeUnixTimeInMs": 0,
                    "additionalProperties": {}
                },
                {
                    "name": "NestedWorkflowOutput",
                    "value": null,
                    "type": null,
                    "isMandatory": false,
                    "defaultValue": null,
                    "id": 0,
                    "creationTimeUnixTimeInMs": 0,
                    "modificationTimeUnixTimeInMs": 0,
                    "additionalProperties": {}
                }
            ],
            "autoSkipOnFailure": false,
            "isDebugMockData": false,
            "debugData": null,
            "parentStepContainerId": null,
            "workflowIdentifier": "317ea3fc-e72c-4c6f-a89f-c621142a785a",
            "isTouchedByAi": false,
            "startLoopStepIdentifier": null,
            "id": 0,
            "creationTimeUnixTimeInMs": 1751277286145,
            "modificationTimeUnixTimeInMs": 1751277776254,
            "additionalProperties": {}
        },
        {
            "parallelActions": [],
            "identifier": "b4315e11-e126-4783-8651-f21ebb69184c",
            "originalStepIdentifier": "b4315e11-e126-4783-8651-f21ebb69184c",
            "isAutomatic": true,
            "isSkippable": false,
            "instanceName": "VirusTotalV3_Add Vote To Entity_1",
            "name": "VirusTotalV3_Add Vote To Entity",
            "integration": "VirusTotalV3",
            "description": "Add a vote to entities in VirusTotal. Supported entities: File Hash, URL, Hostname, Domain, IP Address. Note: only MD5, SHA-1 and SHA-256 Hash types are supported",
            "actionProvider": "Scripts",
            "actionName": "VirusTotalV3_Add Vote To Entity",
            "type": 0,
            "parameters": [
                {
                    "name": "AssignedUsers",
                    "value": null,
                    "type": null,
                    "isMandatory": false,
                    "defaultValue": null,
                    "id": 0,
                    "creationTimeUnixTimeInMs": 0,
                    "modificationTimeUnixTimeInMs": 0,
                    "additionalProperties": {}
                },
                {
                    "name": "DynamicInjectionInstancePlaceholder",
                    "value": "",
                    "type": null,
                    "isMandatory": false,
                    "defaultValue": null,
                    "id": 0,
                    "creationTimeUnixTimeInMs": 0,
                    "modificationTimeUnixTimeInMs": 0,
                    "additionalProperties": {}
                },
                {
                    "name": "FallbackIntegrationInstance",
                    "value": "5223c91d-c832-44cf-87a1-e2a3dbe0c26c",
                    "type": null,
                    "isMandatory": false,
                    "defaultValue": null,
                    "id": 0,
                    "creationTimeUnixTimeInMs": 0,
                    "modificationTimeUnixTimeInMs": 0,
                    "additionalProperties": {},
                    "FallbackInstanceDisplayName": "VirusTotalV3_3"
                },
                {
                    "name": "FetchInstanceByName",
                    "value": "false",
                    "type": null,
                    "isMandatory": false,
                    "defaultValue": null,
                    "id": 0,
                    "creationTimeUnixTimeInMs": 0,
                    "modificationTimeUnixTimeInMs": 0,
                    "additionalProperties": {}
                },
                {
                    "name": "HasApprovalLink",
                    "value": null,
                    "type": null,
                    "isMandatory": false,
                    "defaultValue": null,
                    "id": 0,
                    "creationTimeUnixTimeInMs": 0,
                    "modificationTimeUnixTimeInMs": 0,
                    "additionalProperties": {}
                },
                {
                    "name": "IntegrationInstance",
                    "value": "AutomaticEnvironment",
                    "type": null,
                    "isMandatory": false,
                    "defaultValue": null,
                    "id": 0,
                    "creationTimeUnixTimeInMs": 0,
                    "modificationTimeUnixTimeInMs": 0,
                    "additionalProperties": {}
                },
                {
                    "name": "MessageToAssignee",
                    "value": null,
                    "type": null,
                    "isMandatory": false,
                    "defaultValue": null,
                    "id": 0,
                    "creationTimeUnixTimeInMs": 0,
                    "modificationTimeUnixTimeInMs": 0,
                    "additionalProperties": {}
                },
                {
                    "name": "PendingActionTimeout",
                    "value": null,
                    "type": null,
                    "isMandatory": false,
                    "defaultValue": null,
                    "id": 0,
                    "creationTimeUnixTimeInMs": 0,
                    "modificationTimeUnixTimeInMs": 0,
                    "additionalProperties": {}
                },
                {
                    "name": "ScriptName",
                    "value": "VirusTotalV3_Add Vote To Entity",
                    "type": null,
                    "isMandatory": false,
                    "defaultValue": null,
                    "id": 0,
                    "creationTimeUnixTimeInMs": 0,
                    "modificationTimeUnixTimeInMs": 0,
                    "additionalProperties": {}
                },
                {
                    "name": "ScriptParametersEntityFields",
                    "value": "{\"Vote\":\"Malicious\"}",
                    "type": null,
                    "isMandatory": false,
                    "defaultValue": null,
                    "id": 0,
                    "creationTimeUnixTimeInMs": 0,
                    "modificationTimeUnixTimeInMs": 0,
                    "additionalProperties": {}
                },
                {
                    "name": "SelectedScopeName",
                    "value": "All entities",
                    "type": null,
                    "isMandatory": false,
                    "defaultValue": null,
                    "id": 0,
                    "creationTimeUnixTimeInMs": 0,
                    "modificationTimeUnixTimeInMs": 0,
                    "additionalProperties": {}
                },
                {
                    "name": "UseEntitiesLoopScope",
                    "value": null,
                    "type": null,
                    "isMandatory": false,
                    "defaultValue": null,
                    "id": 0,
                    "creationTimeUnixTimeInMs": 0,
                    "modificationTimeUnixTimeInMs": 0,
                    "additionalProperties": {}
                }
            ],
            "autoSkipOnFailure": false,
            "isDebugMockData": false,
            "debugData": null,
            "parentStepContainerId": null,
            "workflowIdentifier": "317ea3fc-e72c-4c6f-a89f-c621142a785a",
            "isTouchedByAi": false,
            "startLoopStepIdentifier": null,
            "id": 0,
            "creationTimeUnixTimeInMs": 1751277286145,
            "modificationTimeUnixTimeInMs": 1751277286145,
            "additionalProperties": {}
        }
    ],
    "stepsRelations": [
        {
            "condition": "",
            "fromStep": "25598f92-e1bb-44f3-9aa7-3d0fa9f3608d",
            "toStep": "14936ab1-45ce-4897-853c-948e168a4c9f",
            "destinationActionStatus": 0
        },
        {
            "condition": "",
            "fromStep": "b4315e11-e126-4783-8651-f21ebb69184c",
            "toStep": "25598f92-e1bb-44f3-9aa7-3d0fa9f3608d",
            "destinationActionStatus": 0
        },
        {
            "condition": "",
            "fromStep": "1c9341ea-f3e6-4f83-a517-289427e1fb0c",
            "toStep": "b4315e11-e126-4783-8651-f21ebb69184c",
            "destinationActionStatus": 0
        }
    ],
    "templateName": null,
    "playbookType": 0,
    "debugData": {
        "debugBaseAlertId": null,
        "debugAlertId": null
    },
    "entityAccessLevel": 2,
    "defaultAccessLevel": 2,
    "permissions": [],
    "overviewTemplates": [],
    "creationSource": 1
}