[
    {
        "rootCause": "Human error",
        "forCloseReason": 1,
        "id": 16,
        "creationTimeUnixTimeInMs": 1739776836997,
        "modificationTimeUnixTimeInMs": 1741589072970
    },
    {
        "rootCause": "Employee error",
        "forCloseReason": 1,
        "id": 17,
        "creationTimeUnixTimeInMs": 1739776836997,
        "modificationTimeUnixTimeInMs": 1741589072997
    },
    {
        "rootCause": "Other",
        "forCloseReason": 1,
        "id": 18,
        "creationTimeUnixTimeInMs": 1739776836997,
        "modificationTimeUnixTimeInMs": 1741589073022
    },
    {
        "rootCause": "User mistake",
        "forCloseReason": 1,
        "id": 19,
        "creationTimeUnixTimeInMs": 1739776836997,
        "modificationTimeUnixTimeInMs": 1741589073049
    },
    {
        "rootCause": "Normal behavior",
        "forCloseReason": 1,
        "id": 20,
        "creationTimeUnixTimeInMs": 1739776836997,
        "modificationTimeUnixTimeInMs": 1741589073080
    },
    {
        "rootCause": "Lab test",
        "forCloseReason": 1,
        "id": 21,
        "creationTimeUnixTimeInMs": 1739776836997,
        "modificationTimeUnixTimeInMs": 1741589073105
    },
    {
        "rootCause": "Penetration test",
        "forCloseReason": 1,
        "id": 22,
        "creationTimeUnixTimeInMs": 1739776836997,
        "modificationTimeUnixTimeInMs": 1741589073138
    },
    {
        "rootCause": "Rule under construction",
        "forCloseReason": 1,
        "id": 23,
        "creationTimeUnixTimeInMs": 1739776836997,
        "modificationTimeUnixTimeInMs": 1741589073180
    },
    {
        "rootCause": "Rule under construction",
        "forCloseReason": 2,
        "id": 24,
        "creationTimeUnixTimeInMs": 1739776836997,
        "modificationTimeUnixTimeInMs": 1741589073217
    },
    {
        "rootCause": "Lab test",
        "forCloseReason": 2,
        "id": 25,
        "creationTimeUnixTimeInMs": 1739776836997,
        "modificationTimeUnixTimeInMs": 1741589073257
    },
    {
        "rootCause": "Other",
        "forCloseReason": 2,
        "id": 26,
        "creationTimeUnixTimeInMs": 1739776836997,
        "modificationTimeUnixTimeInMs": 1741589073288
    },
    {
        "rootCause": "No clear conclusion",
        "forCloseReason": 3,
        "id": 27,
        "creationTimeUnixTimeInMs": 1739776836997,
        "modificationTimeUnixTimeInMs": 1741589073327
    },
    {
        "rootCause": "External attack",
        "forCloseReason": 0,
        "id": 1,
        "creationTimeUnixTimeInMs": 1739776836997,
        "modificationTimeUnixTimeInMs": 1741589073388
    },
    {
        "rootCause": "System/application malfunction",
        "forCloseReason": 0,
        "id": 2,
        "creationTimeUnixTimeInMs": 1739776836997,
        "modificationTimeUnixTimeInMs": 1741589073420
    },
    {
        "rootCause": "Unforeseen effects of change",
        "forCloseReason": 0,
        "id": 3,
        "creationTimeUnixTimeInMs": 1739776836997,
        "modificationTimeUnixTimeInMs": 1741589073453
    },
    {
        "rootCause": "Irrelevant TCP/UDP port",
        "forCloseReason": 0,
        "id": 4,
        "creationTimeUnixTimeInMs": 1739776836997,
        "modificationTimeUnixTimeInMs": 1741589073487
    },
    {
        "rootCause": "System blocked the attack",
        "forCloseReason": 0,
        "id": 5,
        "creationTimeUnixTimeInMs": 1739776836997,
        "modificationTimeUnixTimeInMs": 1741589073515
    },
    {
        "rootCause": "Infrastructure issue",
        "forCloseReason": 0,
        "id": 6,
        "creationTimeUnixTimeInMs": 1739776836997,
        "modificationTimeUnixTimeInMs": 1741589073544
    },
    {
        "rootCause": "Misconfigured system",
        "forCloseReason": 0,
        "id": 7,
        "creationTimeUnixTimeInMs": 1739776836997,
        "modificationTimeUnixTimeInMs": 1741589073579
    },
    {
        "rootCause": "Similar case is already under investigation",
        "forCloseReason": 0,
        "id": 8,
        "creationTimeUnixTimeInMs": 1739776836997,
        "modificationTimeUnixTimeInMs": 1741589073605
    },
    {
        "rootCause": "Unknown",
        "forCloseReason": 0,
        "id": 9,
        "creationTimeUnixTimeInMs": 1739776836997,
        "modificationTimeUnixTimeInMs": 1741589073671
    },
    {
        "rootCause": "Other",
        "forCloseReason": 0,
        "id": 10,
        "creationTimeUnixTimeInMs": 1739776836997,
        "modificationTimeUnixTimeInMs": 1741589072800
    },
    {
        "rootCause": "Similar case is already under investigation",
        "forCloseReason": 1,
        "id": 11,
        "creationTimeUnixTimeInMs": 1739776836997,
        "modificationTimeUnixTimeInMs": 1741589072831
    },
    {
        "rootCause": "Legit action",
        "forCloseReason": 1,
        "id": 12,
        "creationTimeUnixTimeInMs": 1739776836997,
        "modificationTimeUnixTimeInMs": 1741589072855
    },
    {
        "rootCause": "None",
        "forCloseReason": 1,
        "id": 13,
        "creationTimeUnixTimeInMs": 1739776836997,
        "modificationTimeUnixTimeInMs": 1741589072884
    },
    {
        "rootCause": "Unknown",
        "forCloseReason": 1,
        "id": 14,
        "creationTimeUnixTimeInMs": 1739776836997,
        "modificationTimeUnixTimeInMs": 1741589072906
    },
    {
        "rootCause": "Misconfigured system",
        "forCloseReason": 1,
        "id": 15,
        "creationTimeUnixTimeInMs": 1739776836997,
        "modificationTimeUnixTimeInMs": 1741589072940
    }
]