{
    "id": 0,
    "identifier": "7cf93504-1065-4ac6-a337-b0a25396e7cf",
    "version": "1",
    "isEnabled": true,
    "isDebugMode": false,
    "name": "Playbook_Actions_3",
    "creator": "973d7959-bcd7-48fa-8b56-37fa8244951d",
    "modifiedBy": "973d7959-bcd7-48fa-8b56-37fa8244951d",
    "priority": 2,
    "description": "",
    "environments": [
        "*"
    ],
    "categoryName": "Default",
    "categoryId": 1,
    "originalPlaybookIdentifier": "7cf93504-1065-4ac6-a337-b0a25396e7cf",
    "creationTimeUnixTimeInMs": 1751218788112,
    "modificationTimeUnixTimeInMs": 1751218788112,
    "trigger": {
        "id": 0,
        "identifier": "9f1f1211-96df-43a5-aea1-3f0a21f2e191",
        "type": 8,
        "logicalOperator": 0,
        "conditions": [
            {
                "fieldName": "",
                "value": "",
                "matchType": 0
            }
        ]
    },
    "steps": [
        {
            "parallelActions": [],
            "identifier": "08671054-5440-45a4-802e-03cc6a417130",
            "originalStepIdentifier": "08671054-5440-45a4-802e-03cc6a417130",
            "isAutomatic": true,
            "isSkippable": false,
            "instanceName": "VirusTotalV3_Get Domain Details_1",
            "name": "VirusTotalV3_Get Domain Details",
            "integration": "VirusTotalV3",
            "description": "Get detailed information about the domain using information from VirusTotal. Supported entities: URL (entity extracts domain part), Hostname, Domain.",
            "actionProvider": "Scripts",
            "actionName": "VirusTotalV3_Get Domain Details",
            "type": 0,
            "parameters": [
                {
                    "name": "AssignedUsers",
                    "value": null,
                    "type": null,
                    "isMandatory": false,
                    "defaultValue": null,
                    "id": 0,
                    "creationTimeUnixTimeInMs": 0,
                    "modificationTimeUnixTimeInMs": 0,
                    "additionalProperties": {}
                },
                {
                    "name": "DynamicInjectionInstancePlaceholder",
                    "value": "",
                    "type": null,
                    "isMandatory": false,
                    "defaultValue": null,
                    "id": 0,
                    "creationTimeUnixTimeInMs": 0,
                    "modificationTimeUnixTimeInMs": 0,
                    "additionalProperties": {}
                },
                {
                    "name": "FallbackIntegrationInstance",
                    "value": "74f874b3-c98a-413b-99bb-845f8fecc5c8",
                    "type": null,
                    "isMandatory": false,
                    "defaultValue": null,
                    "id": 0,
                    "creationTimeUnixTimeInMs": 0,
                    "modificationTimeUnixTimeInMs": 0,
                    "additionalProperties": {},
                    "FallbackInstanceDisplayName": "VirusTotalV3_4"
                },
                {
                    "name": "FetchInstanceByName",
                    "value": "false",
                    "type": null,
                    "isMandatory": false,
                    "defaultValue": null,
                    "id": 0,
                    "creationTimeUnixTimeInMs": 0,
                    "modificationTimeUnixTimeInMs": 0,
                    "additionalProperties": {}
                },
                {
                    "name": "HasApprovalLink",
                    "value": null,
                    "type": null,
                    "isMandatory": false,
                    "defaultValue": null,
                    "id": 0,
                    "creationTimeUnixTimeInMs": 0,
                    "modificationTimeUnixTimeInMs": 0,
                    "additionalProperties": {}
                },
                {
                    "name": "IntegrationInstance",
                    "value": "AutomaticEnvironment",
                    "type": null,
                    "isMandatory": false,
                    "defaultValue": null,
                    "id": 0,
                    "creationTimeUnixTimeInMs": 0,
                    "modificationTimeUnixTimeInMs": 0,
                    "additionalProperties": {}
                },
                {
                    "name": "MessageToAssignee",
                    "value": null,
                    "type": null,
                    "isMandatory": false,
                    "defaultValue": null,
                    "id": 0,
                    "creationTimeUnixTimeInMs": 0,
                    "modificationTimeUnixTimeInMs": 0,
                    "additionalProperties": {}
                },
                {
                    "name": "PendingActionTimeout",
                    "value": null,
                    "type": null,
                    "isMandatory": false,
                    "defaultValue": null,
                    "id": 0,
                    "creationTimeUnixTimeInMs": 0,
                    "modificationTimeUnixTimeInMs": 0,
                    "additionalProperties": {}
                },
                {
                    "name": "ScriptName",
                    "value": "VirusTotalV3_Get Domain Details",
                    "type": null,
                    "isMandatory": false,
                    "defaultValue": null,
                    "id": 0,
                    "creationTimeUnixTimeInMs": 0,
                    "modificationTimeUnixTimeInMs": 0,
                    "additionalProperties": {}
                },
                {
                    "name": "ScriptParametersEntityFields",
                    "value": "{\"Engine Threshold\":\"1\",\"Engine Percentage Threshold\":\"1\",\"Engine Whitelist\":\"\",\"Retrieve Comments\":true,\"Create Insight\":true,\"Only Suspicious Entity Insight\":false,\"Max Comments To Return\":\"10\",\"Widget Theme\":\"Dark\",\"Fetch Widget\":true}",
                    "type": null,
                    "isMandatory": false,
                    "defaultValue": null,
                    "id": 0,
                    "creationTimeUnixTimeInMs": 0,
                    "modificationTimeUnixTimeInMs": 0,
                    "additionalProperties": {}
                },
                {
                    "name": "SelectedScopeName",
                    "value": "All entities",
                    "type": null,
                    "isMandatory": false,
                    "defaultValue": null,
                    "id": 0,
                    "creationTimeUnixTimeInMs": 0,
                    "modificationTimeUnixTimeInMs": 0,
                    "additionalProperties": {}
                },
                {
                    "name": "UseEntitiesLoopScope",
                    "value": null,
                    "type": null,
                    "isMandatory": false,
                    "defaultValue": null,
                    "id": 0,
                    "creationTimeUnixTimeInMs": 0,
                    "modificationTimeUnixTimeInMs": 0,
                    "additionalProperties": {}
                }
            ],
            "autoSkipOnFailure": false,
            "isDebugMockData": false,
            "debugData": null,
            "parentStepContainerId": null,
            "workflowIdentifier": "7cf93504-1065-4ac6-a337-b0a25396e7cf",
            "isTouchedByAi": false,
            "startLoopStepIdentifier": null,
            "id": 0,
            "creationTimeUnixTimeInMs": 1751218788112,
            "modificationTimeUnixTimeInMs": 1751218788112,
            "additionalProperties": {}
        },
        {
            "parallelActions": [],
            "identifier": "adfd2092-8cdf-4a74-886a-095ef26b01cb",
            "originalStepIdentifier": "adfd2092-8cdf-4a74-886a-095ef26b01cb",
            "isAutomatic": true,
            "isSkippable": false,
            "instanceName": "VirusTotalV3_Get Related Domains_1",
            "name": "VirusTotalV3_Get Related Domains",
            "integration": "VirusTotalV3",
            "description": "Get related domains to the provided entities from VirusTotal. Note: this action requires a VT Enterprise token. Supported entities: IP, URL, Filehash, Hostname, Domain. Note: only MD5, SHA-1 and SHA-256 are supported.",
            "actionProvider": "Scripts",
            "actionName": "VirusTotalV3_Get Related Domains",
            "type": 0,
            "parameters": [
                {
                    "name": "AssignedUsers",
                    "value": null,
                    "type": null,
                    "isMandatory": false,
                    "defaultValue": null,
                    "id": 0,
                    "creationTimeUnixTimeInMs": 0,
                    "modificationTimeUnixTimeInMs": 0,
                    "additionalProperties": {}
                },
                {
                    "name": "DynamicInjectionInstancePlaceholder",
                    "value": "",
                    "type": null,
                    "isMandatory": false,
                    "defaultValue": null,
                    "id": 0,
                    "creationTimeUnixTimeInMs": 0,
                    "modificationTimeUnixTimeInMs": 0,
                    "additionalProperties": {}
                },
                {
                    "name": "FallbackIntegrationInstance",
                    "value": "74f874b3-c98a-413b-99bb-845f8fecc5c8",
                    "type": null,
                    "isMandatory": false,
                    "defaultValue": null,
                    "id": 0,
                    "creationTimeUnixTimeInMs": 0,
                    "modificationTimeUnixTimeInMs": 0,
                    "additionalProperties": {},
                    "FallbackInstanceDisplayName": "VirusTotalV3_4"
                },
                {
                    "name": "FetchInstanceByName",
                    "value": "false",
                    "type": null,
                    "isMandatory": false,
                    "defaultValue": null,
                    "id": 0,
                    "creationTimeUnixTimeInMs": 0,
                    "modificationTimeUnixTimeInMs": 0,
                    "additionalProperties": {}
                },
                {
                    "name": "HasApprovalLink",
                    "value": null,
                    "type": null,
                    "isMandatory": false,
                    "defaultValue": null,
                    "id": 0,
                    "creationTimeUnixTimeInMs": 0,
                    "modificationTimeUnixTimeInMs": 0,
                    "additionalProperties": {}
                },
                {
                    "name": "IntegrationInstance",
                    "value": "AutomaticEnvironment",
                    "type": null,
                    "isMandatory": false,
                    "defaultValue": null,
                    "id": 0,
                    "creationTimeUnixTimeInMs": 0,
                    "modificationTimeUnixTimeInMs": 0,
                    "additionalProperties": {}
                },
                {
                    "name": "MessageToAssignee",
                    "value": null,
                    "type": null,
                    "isMandatory": false,
                    "defaultValue": null,
                    "id": 0,
                    "creationTimeUnixTimeInMs": 0,
                    "modificationTimeUnixTimeInMs": 0,
                    "additionalProperties": {}
                },
                {
                    "name": "PendingActionTimeout",
                    "value": null,
                    "type": null,
                    "isMandatory": false,
                    "defaultValue": null,
                    "id": 0,
                    "creationTimeUnixTimeInMs": 0,
                    "modificationTimeUnixTimeInMs": 0,
                    "additionalProperties": {}
                },
                {
                    "name": "ScriptName",
                    "value": "VirusTotalV3_Get Related Domains",
                    "type": null,
                    "isMandatory": false,
                    "defaultValue": null,
                    "id": 0,
                    "creationTimeUnixTimeInMs": 0,
                    "modificationTimeUnixTimeInMs": 0,
                    "additionalProperties": {}
                },
                {
                    "name": "ScriptParametersEntityFields",
                    "value": "{\"Results\":\"Combined\",\"Max Domains To Return\":\"40\"}",
                    "type": null,
                    "isMandatory": false,
                    "defaultValue": null,
                    "id": 0,
                    "creationTimeUnixTimeInMs": 0,
                    "modificationTimeUnixTimeInMs": 0,
                    "additionalProperties": {}
                },
                {
                    "name": "SelectedScopeName",
                    "value": "All entities",
                    "type": null,
                    "isMandatory": false,
                    "defaultValue": null,
                    "id": 0,
                    "creationTimeUnixTimeInMs": 0,
                    "modificationTimeUnixTimeInMs": 0,
                    "additionalProperties": {}
                },
                {
                    "name": "UseEntitiesLoopScope",
                    "value": null,
                    "type": null,
                    "isMandatory": false,
                    "defaultValue": null,
                    "id": 0,
                    "creationTimeUnixTimeInMs": 0,
                    "modificationTimeUnixTimeInMs": 0,
                    "additionalProperties": {}
                }
            ],
            "autoSkipOnFailure": false,
            "isDebugMockData": false,
            "debugData": null,
            "parentStepContainerId": null,
            "workflowIdentifier": "7cf93504-1065-4ac6-a337-b0a25396e7cf",
            "isTouchedByAi": false,
            "startLoopStepIdentifier": null,
            "id": 0,
            "creationTimeUnixTimeInMs": 1751218788112,
            "modificationTimeUnixTimeInMs": 1751218788112,
            "additionalProperties": {}
        }
    ],
    "stepsRelations": [
        {
            "condition": "",
            "fromStep": "08671054-5440-45a4-802e-03cc6a417130",
            "toStep": "adfd2092-8cdf-4a74-886a-095ef26b01cb",
            "destinationActionStatus": 0
        }
    ],
    "templateName": null,
    "playbookType": 0,
    "debugData": {
        "debugBaseAlertId": null,
        "debugAlertId": null
    },
    "entityAccessLevel": 2,
    "defaultAccessLevel": 2,
    "permissions": [],
    "overviewTemplates": [],
    "creationSource": 1
}